solana_chart/__init__.py
solana_chart/prices.py
solana_chart-0.0.3.dist-info/METADATA
solana_chart-0.0.3.dist-info/WHEEL
solana_chart-0.0.3.dist-info/top_level.txt
solana_chart-0.0.3.dist-info/RECORD
