Metadata-Version: 2.4
Name: solana-chart
Version: 0.0.3
Summary: Solana chart package
Classifier: Programming Language :: Python :: 3
Classifier: Operating System :: OS Independent
Requires-Python: >=3.9
